bigslice/__init__.py
bigslice/bigslice
bigslice/download_bigslice_hmmdb
bigslice/vectorize_bgcs
bigslice/db/__init__.py
bigslice/modules/__init__.py
bigslice/modules/utils.py
bigslice/modules/clustering/__init__.py
bigslice/modules/clustering/birch.py
bigslice/modules/clustering/membership.py
bigslice/modules/data/__init__.py
bigslice/modules/data/bgc.py
bigslice/modules/data/chem_class_map.tsv
bigslice/modules/data/database.py
bigslice/modules/data/features.py
bigslice/modules/data/hmm.py
bigslice/modules/data/hsp.py
bigslice/modules/data/official_models.json
bigslice/modules/data/run.py
bigslice/modules/data/schema.sql
bigslice/modules/data/schema_query_mode.sql
bigslice/modules/data/schema_reports_index.sql
bigslice/modules/data/taxonomy.py
bigslice/modules/output/__init__.py
bigslice/modules/output/csv/__init__.py
bigslice/modules/output/flask_app/LICENSE.txt
bigslice/modules/output/flask_app/__init__.py
bigslice/modules/output/flask_app/requirements.txt
bigslice/modules/output/flask_app/start_server.sh
bigslice/modules/output/flask_app/app/__init__.py
bigslice/modules/output/flask_app/app/config.py
bigslice/modules/output/flask_app/app/run.py
bigslice/modules/output/flask_app/app/controllers/__init__.py
bigslice/modules/output/flask_app/app/controllers/about.py
bigslice/modules/output/flask_app/app/controllers/bgc.py
bigslice/modules/output/flask_app/app/controllers/dataset.py
bigslice/modules/output/flask_app/app/controllers/feedback.py
bigslice/modules/output/flask_app/app/controllers/gcf.py
bigslice/modules/output/flask_app/app/controllers/help_me.py
bigslice/modules/output/flask_app/app/controllers/root.py
bigslice/modules/output/flask_app/app/controllers/run.py
bigslice/modules/output/flask_app/app/controllers/summary.py
bigslice/modules/output/flask_app/app/controllers/reports/__init__.py
bigslice/modules/output/flask_app/app/controllers/reports/main.py
bigslice/modules/output/flask_app/app/controllers/reports/query.py
bigslice-2.0.2.dist-info/licenses/LICENSE.txt
bigslice-2.0.2.dist-info/METADATA
bigslice-2.0.2.dist-info/WHEEL
bigslice-2.0.2.dist-info/top_level.txt
bigslice-2.0.2.dist-info/RECORD
