Metadata-Version: 2.4
Name: bigslice
Version: 2.0.2
Summary: A highly scalable, user-interactive tool for the large scale analysis of Biosynthetic Gene Clusters data
Home-page: https://github.com/satriaphd/bigslice
Author: Satria A. Kautsar
Author-email: satriaphd@gmail.com
Classifier: Programming Language :: Python :: 3
Requires-Python: >=3.7
License-File: LICENSE.txt
Requires-Dist: pyhmmer
Requires-Dist: biopython<=1.83,>=1.73
Requires-Dist: numpy
Requires-Dist: pandas
Requires-Dist: scikit-learn
Requires-Dist: tqdm
Requires-Dist: pyarrow
Dynamic: author
Dynamic: author-email
Dynamic: classifier
Dynamic: description
Dynamic: home-page
Dynamic: license-file
Dynamic: requires-dist
Dynamic: requires-python
Dynamic: summary
